LICENSE
noita_save_manager/__init__.py
noita_save_manager/save_manager.py
noita_save_manager-0.1.4.dist-info/entry_points.txt
noita_save_manager-0.1.4.dist-info/LICENSE
noita_save_manager-0.1.4.dist-info/WHEEL
noita_save_manager-0.1.4.dist-info/METADATA
noita_save_manager-0.1.4.dist-info/RECORD
