Metadata-Version: 2.1
Name: noita-save-manager
Version: 0.1.4
Summary: Noita Save Manager, allows for backup and restoring of save files
Home-page: https://github.com/mcgillij/noita_save_manager
License: MIT
Keywords: noita,save,backup,restore,manager
Author: mcgillij
Author-email: mcgillivray.jason@gmail.com
Requires-Python: >=3.9,<4.0
Classifier: Intended Audience :: End Users/Desktop
Classifier: License :: OSI Approved :: MIT License
Classifier: Natural Language :: English
Classifier: Operating System :: Microsoft :: Windows :: Windows 10
Classifier: Operating System :: POSIX :: Linux
Classifier: Programming Language :: Python :: 3
Classifier: Programming Language :: Python :: 3.9
Classifier: Topic :: Games/Entertainment
Classifier: Topic :: System :: Archiving :: Backup
Classifier: Topic :: Utilities
Requires-Dist: PySimpleGUI (>=4.34.0,<5.0.0)
Requires-Dist: psutil (>=5.8.0,<6.0.0)
Project-URL: Documentation, https://github.com/mcgillij/noita_save_manager/blob/main/README.md
Project-URL: Repository, https://github.com/mcgillij/noita_save_manager
